tenvs/VERSION.txt
tenvs/__init__.py
tenvs/logger.py
tenvs/market.py
tenvs/market_test.py
tenvs/portfolio.py
tenvs/portfolio_test.py
tenvs/scenario.py
tenvs/envs/__init__.py
tenvs/envs/average.py
tenvs/envs/average_test.py
tenvs/envs/base.py
tenvs/envs/multi_vol.py
tenvs/envs/multi_vol_test.py
tenvs/envs/reward.py
tenvs/envs/reward_test.py
tenvs/envs/simple.py
tenvs/envs/simple_test.py
tenvs-1.0.9.dist-info/LICENSE
tenvs-1.0.9.dist-info/METADATA
tenvs-1.0.9.dist-info/WHEEL
tenvs-1.0.9.dist-info/top_level.txt
tenvs-1.0.9.dist-info/RECORD
