Metadata-Version: 2.1
Name: tenvs
Version: 1.0.9
Summary: UNKNOWN
Home-page: https://github.com/tradingAI/tenvs
Author: liuwen
Author-email: liuwen.w@qq.com
License: UNKNOWN
Platform: UNKNOWN
Classifier: Programming Language :: Python :: 3
Classifier: License :: OSI Approved :: MIT License
Classifier: Operating System :: OS Independent
Requires-Python: >=3
Requires-Dist: beautifulsoup4
Requires-Dist: gym
Requires-Dist: lxml
Requires-Dist: msgpack
Requires-Dist: numpy
Requires-Dist: pytest
Requires-Dist: pytest-cov
Requires-Dist: pandas
Requires-Dist: requests
Requires-Dist: scipy
Requires-Dist: simplejson
Requires-Dist: tushare
